pylatconverter/__init__.py
pylatconverter/main.py
pylatconverter/pylatconverter.py
pylatconverter-0.1.10.dist-info/DESCRIPTION.rst
pylatconverter-0.1.10.dist-info/METADATA
pylatconverter-0.1.10.dist-info/RECORD
pylatconverter-0.1.10.dist-info/WHEEL
pylatconverter-0.1.10.dist-info/metadata.json
pylatconverter-0.1.10.dist-info/top_level.txt
