Metadata-Version: 2.0
Name: pylatconverter
Version: 0.1.10
Summary: Convert your variables into latex code
Home-page: https://github.com/FSalema/pylatconverter
Author: Francisco Salema
Author-email: x_salema@hotmail.com
License: MIT license
Keywords: pylatconverter
Platform: UNKNOWN
Classifier: Development Status :: 2 - Pre-Alpha
Classifier: Intended Audience :: Developers
Classifier: License :: OSI Approved :: MIT License
Classifier: Natural Language :: English
Classifier: Programming Language :: Python :: 2
Classifier: Programming Language :: Python :: 2.6
Classifier: Programming Language :: Python :: 2.7
Classifier: Programming Language :: Python :: 3
Classifier: Programming Language :: Python :: 3.3
Classifier: Programming Language :: Python :: 3.4
Classifier: Programming Language :: Python :: 3.5
